LICENSE
README.md
setup.py
ToyBase/ToyBase.py
ToyBase/__init__.py
ToyBase.egg-info/PKG-INFO
ToyBase.egg-info/SOURCES.txt
ToyBase.egg-info/dependency_links.txt
ToyBase.egg-info/top_level.txt