Metadata-Version: 2.1
Name: ToyBase
Version: 1.0.3
Summary: A Toy Database System written in Python
Home-page: https://github.com/Sas2k/ToyBase
Author: Sasen Perera
Author-email: sas8.communications@gmail.com
License-File: LICENSE
